{".class":"MypyFile","_fullname":"index_navigator","future_import_flags":[],"is_partial_stub_package":false,"is_stub":false,"names":{".class":"SymbolTable","IndexNavigator":{".class":"SymbolTableNode","kind":"Gdef","node":{".class":"TypeInfo","_promote":[],"abstract_attributes":[],"alt_promote":null,"bases":["builtins.object"],"dataclass_transform_spec":null,"declared_metaclass":null,"defn":{".class":"ClassDef","fullname":"index_navigator.IndexNavigator","name":"IndexNavigator","type_vars":[]},"deletable_attributes":[],"deprecated":null,"flags":[],"fullname":"index_navigator.IndexNavigator","has_param_spec_type":false,"metaclass_type":null,"metadata":{},"module_name":"index_navigator","mro":["index_navigator.IndexNavigator","builtins.object"],"names":{".class":"SymbolTable","__enter__":{".class":"SymbolTableNode","kind":"Mdef","node":{".class":"FuncDef","abstract_status":0,"arg_kinds":[0],"arg_names":[null],"dataclass_transform_spec":null,"deprecated":null,"flags":["is_trivial_self"],"fullname":"index_navigator.IndexNavigator.__enter__","name":"__enter__","original_first_arg":"self","type":{".class":"CallableType","arg_kinds":[0],"arg_names":[null],"arg_types":["index_navigator.IndexNavigator"],"fallback":"builtins.function","from_concatenate":false,"implicit":false,"imprecise_arg_kinds":false,"is_bound":false,"is_ellipsis_args":false,"name":"__enter__ of IndexNavigator","ret_type":"index_navigator.IndexNavigator","type_guard":null,"type_is":null,"unpack_kwargs":false,"variables":[]}}},"__exit__":{".class":"SymbolTableNode","kind":"Mdef","node":{".class":"FuncDef","abstract_status":0,"arg_kinds":[0,0,0,0],"arg_names":[null,null,null,null],"dataclass_transform_spec":null,"deprecated":null,"flags":["is_trivial_self"],"fullname":"index_navigator.IndexNavigator.__exit__","name":"__exit__","original_first_arg":"self","type":{".class":"CallableType","arg_kinds":[0,0,0,0],"arg_names":[null,null,null,null],"arg_types":["index_navigator.IndexNavigator","builtins.object","builtins.object","builtins.object"],"fallback":"builtins.function","from_concatenate":false,"implicit":false,"imprecise_arg_kinds":false,"is_bound":false,"is_ellipsis_args":false,"name":"__exit__ of IndexNavigator","ret_type":{".class":"NoneType"},"type_guard":null,"type_is":null,"unpack_kwargs":false,"variables":[]}}},"__init__":{".class":"SymbolTableNode","kind":"Mdef","node":{".class":"FuncDef","abstract_status":0,"arg_kinds":[0,0],"arg_names":["self","index_path"],"dataclass_transform_spec":null,"deprecated":null,"flags":["is_trivial_self"],"fullname":"index_navigator.IndexNavigator.__init__","name":"__init__","original_first_arg":"self","type":{".class":"CallableType","arg_kinds":[0,0],"arg_names":["self","index_path"],"arg_types":["index_navigator.IndexNavigator","builtins.str"],"fallback":"builtins.function","from_concatenate":false,"implicit":false,"imprecise_arg_kinds":false,"is_bound":false,"is_ellipsis_args":false,"name":"__init__ of IndexNavigator","ret_type":{".class":"NoneType"},"type_guard":null,"type_is":null,"unpack_kwargs":false,"variables":[]}}},"_fh":{".class":"SymbolTableNode","implicit":true,"kind":"Mdef","node":{".class":"Var","flags":["is_ready","is_inferred"],"fullname":"index_navigator.IndexNavigator._fh","name":"_fh","setter_type":null,"type":"_io.BufferedRandom"}},"_format_record":{".class":"SymbolTableNode","kind":"Mdef","node":{".class":"FuncDef","abstract_status":0,"arg_kinds":[0,0,0,0],"arg_names":["self","word","offset","length"],"dataclass_transform_spec":null,"deprecated":null,"flags":["is_trivial_self"],"fullname":"index_navigator.IndexNavigator._format_record","name":"_format_record","original_first_arg":"self","type":{".class":"CallableType","arg_kinds":[0,0,0,0],"arg_names":["self","word","offset","length"],"arg_types":["index_navigator.IndexNavigator","builtins.str","builtins.int","builtins.int"],"fallback":"builtins.function","from_concatenate":false,"implicit":false,"imprecise_arg_kinds":false,"is_bound":false,"is_ellipsis_args":false,"name":"_format_record of IndexNavigator","ret_type":"builtins.bytes","type_guard":null,"type_is":null,"unpack_kwargs":false,"variables":[]}}},"_index_path":{".class":"SymbolTableNode","implicit":true,"kind":"Mdef","node":{".class":"Var","flags":["explicit_self_type","is_ready","is_inferred"],"fullname":"index_navigator.IndexNavigator._index_path","name":"_index_path","setter_type":null,"type":"builtins.str"}},"_n_records":{".class":"SymbolTableNode","implicit":true,"kind":"Mdef","node":{".class":"Var","flags":["explicit_self_type","is_ready","is_inferred"],"fullname":"index_navigator.IndexNavigator._n_records","name":"_n_records","setter_type":null,"type":"builtins.int"}},"_read_record":{".class":"SymbolTableNode","kind":"Mdef","node":{".class":"FuncDef","abstract_status":0,"arg_kinds":[0,0],"arg_names":["self","record_no"],"dataclass_transform_spec":null,"deprecated":null,"flags":["is_trivial_self"],"fullname":"index_navigator.IndexNavigator._read_record","name":"_read_record","original_first_arg":"self","type":{".class":"CallableType","arg_kinds":[0,0],"arg_names":["self","record_no"],"arg_types":["index_navigator.IndexNavigator","builtins.int"],"fallback":"builtins.function","from_concatenate":false,"implicit":false,"imprecise_arg_kinds":false,"is_bound":false,"is_ellipsis_args":false,"name":"_read_record of IndexNavigator","ret_type":{".class":"UnionType","items":[{".class":"TupleType","implicit":false,"items":["builtins.str","builtins.int","builtins.int"],"partial_fallback":{".class":"Instance","args":[{".class":"AnyType","missing_import_name":null,"source_any":null,"type_of_any":6}],"extra_attrs":null,"type_ref":"builtins.tuple"}},{".class":"NoneType"}],"uses_pep604_syntax":false},"type_guard":null,"type_is":null,"unpack_kwargs":false,"variables":[]}}},"_refresh_count":{".class":"SymbolTableNode","kind":"Mdef","node":{".class":"FuncDef","abstract_status":0,"arg_kinds":[0],"arg_names":["self"],"dataclass_transform_spec":null,"deprecated":null,"flags":["is_trivial_self"],"fullname":"index_navigator.IndexNavigator._refresh_count","name":"_refresh_count","original_first_arg":"self","type":{".class":"CallableType","arg_kinds":[0],"arg_names":["self"],"arg_types":["index_navigator.IndexNavigator"],"fallback":"builtins.function","from_concatenate":false,"implicit":false,"imprecise_arg_kinds":false,"is_bound":false,"is_ellipsis_args":false,"name":"_refresh_count of IndexNavigator","ret_type":{".class":"NoneType"},"type_guard":null,"type_is":null,"unpack_kwargs":false,"variables":[]}}},"all_keywords":{".class":"SymbolTableNode","kind":"Mdef","node":{".class":"FuncDef","abstract_status":0,"arg_kinds":[0],"arg_names":["self"],"dataclass_transform_spec":null,"deprecated":null,"flags":["is_trivial_self"],"fullname":"index_navigator.IndexNavigator.all_keywords","name":"all_keywords","original_first_arg":"self","type":{".class":"CallableType","arg_kinds":[0],"arg_names":["self"],"arg_types":["index_navigator.IndexNavigator"],"fallback":"builtins.function","from_concatenate":false,"implicit":false,"imprecise_arg_kinds":false,"is_bound":false,"is_ellipsis_args":false,"name":"all_keywords of IndexNavigator","ret_type":{".class":"Instance","args":[{".class":"AnyType","missing_import_name":null,"source_any":null,"type_of_any":4}],"extra_attrs":null,"type_ref":"builtins.list"},"type_guard":null,"type_is":null,"unpack_kwargs":false,"variables":[]}}},"close":{".class":"SymbolTableNode","kind":"Mdef","node":{".class":"FuncDef","abstract_status":0,"arg_kinds":[0],"arg_names":["self"],"dataclass_transform_spec":null,"deprecated":null,"flags":["is_trivial_self"],"fullname":"index_navigator.IndexNavigator.close","name":"close","original_first_arg":"self","type":{".class":"CallableType","arg_kinds":[0],"arg_names":["self"],"arg_types":["index_navigator.IndexNavigator"],"fallback":"builtins.function","from_concatenate":false,"implicit":false,"imprecise_arg_kinds":false,"is_bound":false,"is_ellipsis_args":false,"name":"close of IndexNavigator","ret_type":{".class":"NoneType"},"type_guard":null,"type_is":null,"unpack_kwargs":false,"variables":[]}}},"find":{".class":"SymbolTableNode","kind":"Mdef","node":{".class":"FuncDef","abstract_status":0,"arg_kinds":[0,0],"arg_names":["self","keyword"],"dataclass_transform_spec":null,"deprecated":null,"flags":["is_trivial_self"],"fullname":"index_navigator.IndexNavigator.find","name":"find","original_first_arg":"self","type":{".class":"CallableType","arg_kinds":[0,0],"arg_names":["self","keyword"],"arg_types":["index_navigator.IndexNavigator","builtins.str"],"fallback":"builtins.function","from_concatenate":false,"implicit":false,"imprecise_arg_kinds":false,"is_bound":false,"is_ellipsis_args":false,"name":"find of IndexNavigator","ret_type":{".class":"UnionType","items":[{".class":"TupleType","implicit":false,"items":["builtins.int","builtins.int"],"partial_fallback":{".class":"Instance","args":[{".class":"AnyType","missing_import_name":null,"source_any":null,"type_of_any":6}],"extra_attrs":null,"type_ref":"builtins.tuple"}},{".class":"NoneType"}],"uses_pep604_syntax":false},"type_guard":null,"type_is":null,"unpack_kwargs":false,"variables":[]}}},"insert_sorted":{".class":"SymbolTableNode","kind":"Mdef","node":{".class":"FuncDef","abstract_status":0,"arg_kinds":[0,0,0,0],"arg_names":["self","keyword","offset","length"],"dataclass_transform_spec":null,"deprecated":null,"flags":["is_trivial_self"],"fullname":"index_navigator.IndexNavigator.insert_sorted","name":"insert_sorted","original_first_arg":"self","type":{".class":"CallableType","arg_kinds":[0,0,0,0],"arg_names":["self","keyword","offset","length"],"arg_types":["index_navigator.IndexNavigator","builtins.str","builtins.int","builtins.int"],"fallback":"builtins.function","from_concatenate":false,"implicit":false,"imprecise_arg_kinds":false,"is_bound":false,"is_ellipsis_args":false,"name":"insert_sorted of IndexNavigator","ret_type":{".class":"NoneType"},"type_guard":null,"type_is":null,"unpack_kwargs":false,"variables":[]}}},"total_records":{".class":"SymbolTableNode","kind":"Mdef","node":{".class":"FuncDef","abstract_status":0,"arg_kinds":[0],"arg_names":["self"],"dataclass_transform_spec":null,"deprecated":null,"flags":["is_trivial_self"],"fullname":"index_navigator.IndexNavigator.total_records","name":"total_records","original_first_arg":"self","type":{".class":"CallableType","arg_kinds":[0],"arg_names":["self"],"arg_types":["index_navigator.IndexNavigator"],"fallback":"builtins.function","from_concatenate":false,"implicit":false,"imprecise_arg_kinds":false,"is_bound":false,"is_ellipsis_args":false,"name":"total_records of IndexNavigator","ret_type":"builtins.int","type_guard":null,"type_is":null,"unpack_kwargs":false,"variables":[]}}}},"self_type":{".class":"TypeVarType","default":{".class":"AnyType","missing_import_name":null,"source_any":null,"type_of_any":4},"fullname":"index_navigator.IndexNavigator.Self","id":0,"name":"Self","namespace":"","upper_bound":"index_navigator.IndexNavigator","values":[],"variance":0},"slots":null,"tuple_type":null,"type_vars":[],"typeddict_type":null}},"KEY_WIDTH":{".class":"SymbolTableNode","kind":"Gdef","node":{".class":"Var","flags":["is_ready","is_inferred","has_explicit_value"],"fullname":"index_navigator.KEY_WIDTH","name":"KEY_WIDTH","setter_type":null,"type":"builtins.int"}},"LEN_WIDTH":{".class":"SymbolTableNode","kind":"Gdef","node":{".class":"Var","flags":["is_ready","is_inferred","has_explicit_value"],"fullname":"index_navigator.LEN_WIDTH","name":"LEN_WIDTH","setter_type":null,"type":"builtins.int"}},"OFF_WIDTH":{".class":"SymbolTableNode","kind":"Gdef","node":{".class":"Var","flags":["is_ready","is_inferred","has_explicit_value"],"fullname":"index_navigator.OFF_WIDTH","name":"OFF_WIDTH","setter_type":null,"type":"builtins.int"}},"Optional":{".class":"SymbolTableNode","cross_ref":"typing.Optional","kind":"Gdef"},"RECORD_SIZE":{".class":"SymbolTableNode","kind":"Gdef","node":{".class":"Var","flags":["is_ready","is_inferred","has_explicit_value"],"fullname":"index_navigator.RECORD_SIZE","name":"RECORD_SIZE","setter_type":null,"type":"builtins.int"}},"Tuple":{".class":"SymbolTableNode","cross_ref":"typing.Tuple","kind":"Gdef"},"__annotations__":{".class":"SymbolTableNode","kind":"Gdef","node":{".class":"Var","flags":["is_ready"],"fullname":"index_navigator.__annotations__","name":"__annotations__","setter_type":null,"type":{".class":"Instance","args":["builtins.str",{".class":"AnyType","missing_import_name":null,"source_any":null,"type_of_any":6}],"extra_attrs":null,"type_ref":"builtins.dict"}}},"__doc__":{".class":"SymbolTableNode","kind":"Gdef","node":{".class":"Var","flags":["is_ready"],"fullname":"index_navigator.__doc__","name":"__doc__","setter_type":null,"type":"builtins.str"}},"__file__":{".class":"SymbolTableNode","kind":"Gdef","node":{".class":"Var","flags":["is_ready"],"fullname":"index_navigator.__file__","name":"__file__","setter_type":null,"type":"builtins.str"}},"__name__":{".class":"SymbolTableNode","kind":"Gdef","node":{".class":"Var","flags":["is_ready"],"fullname":"index_navigator.__name__","name":"__name__","setter_type":null,"type":"builtins.str"}},"__package__":{".class":"SymbolTableNode","kind":"Gdef","node":{".class":"Var","flags":["is_ready"],"fullname":"index_navigator.__package__","name":"__package__","setter_type":null,"type":"builtins.str"}},"__spec__":{".class":"SymbolTableNode","kind":"Gdef","node":{".class":"Var","flags":["is_ready"],"fullname":"index_navigator.__spec__","name":"__spec__","setter_type":null,"type":"_frozen_importlib.ModuleSpec"}},"bisect":{".class":"SymbolTableNode","cross_ref":"bisect","kind":"Gdef"},"os":{".class":"SymbolTableNode","cross_ref":"os","kind":"Gdef"}},"path":"index_navigator.py"}